rfc6266.py
test_rfc6266.py
rfc6266_content_disposition-0.0.6.dist-info/COPYING
rfc6266_content_disposition-0.0.6.dist-info/COPYING.LESSER
rfc6266_content_disposition-0.0.6.dist-info/METADATA
rfc6266_content_disposition-0.0.6.dist-info/WHEEL
rfc6266_content_disposition-0.0.6.dist-info/top_level.txt
rfc6266_content_disposition-0.0.6.dist-info/RECORD
