Metadata-Version: 2.1
Name: rfc6266-content-disposition
Version: 0.0.6
Summary: Parse and generate Content-Disposition headers (a fork maintained by ekzhu)
Home-page: https://github.com/ekzhu/rfc6266
Author: Gabriel de Perthuis, ekzhu
Author-email: g2p.code+rfc6266@gmail.com
License: GNU LGPL
Keywords: rfc6266 Content-Disposition http attachments
Platform: OS-independent
Classifier: Programming Language :: Python :: 2
Classifier: Programming Language :: Python :: 3
Classifier: Programming Language :: Python :: Implementation :: CPython
Classifier: Programming Language :: Python :: Implementation :: PyPy
Classifier: Intended Audience :: Developers
Classifier: License :: OSI Approved :: GNU Library or Lesser General Public License (LGPL)
Classifier: Topic :: Internet :: WWW/HTTP
Requires-Dist: LEPL
